simuhw/__init__.py
simuhw/_adder.py
simuhw/_analyzer.py
simuhw/_base.py
simuhw/_bit_op.py
simuhw/_branch.py
simuhw/_buffer.py
simuhw/_channel.py
simuhw/_clock.py
simuhw/_comparator.py
simuhw/_converter.py
simuhw/_delay.py
simuhw/_divider.py
simuhw/_flipflop.py
simuhw/_gate.py
simuhw/_group.py
simuhw/_latch.py
simuhw/_lut.py
simuhw/_multiplier.py
simuhw/_negator.py
simuhw/_operator.py
simuhw/_remainder.py
simuhw/_shifter.py
simuhw/_simulator.py
simuhw/_subtractor.py
simuhw/_type.py
simuhw/_version.py
simuhw/alu/_74181.py
simuhw/alu/_74182.py
simuhw/alu/__init__.py
simuhw/alu/_full.py
simuhw/alu/_generic.py
simuhw/counter/_74161.py
simuhw/counter/_74163.py
simuhw/counter/__init__.py
simuhw/counter/_base.py
simuhw/fp/__init__.py
simuhw/fp/_adder.py
simuhw/fp/_classifier.py
simuhw/fp/_comparator.py
simuhw/fp/_converter.py
simuhw/fp/_divider.py
simuhw/fp/_multiplier.py
simuhw/fp/_multiply_adder.py
simuhw/fp/_negator.py
simuhw/fp/_operator.py
simuhw/fp/_remainder.py
simuhw/fp/_rounder.py
simuhw/fp/_square_root.py
simuhw/fp/_subtractor.py
simuhw/fp/riscv/__init__.py
simuhw/fp/riscv/_frec7.py
simuhw/fp/riscv/_frsqrt7.py
simuhw/memory/__init__.py
simuhw/memory/_base.py
simuhw/memory/_edge_triggered.py
simuhw/memory/_level_triggered.py
simuhw/memory/model/__init__.py
simuhw/memory/model/_base.py
simuhw/memory/model/_mock.py
simuhw/memory/model/_real.py
simuhw-0.7.3.dist-info/licenses/LICENSE
simuhw-0.7.3.dist-info/METADATA
simuhw-0.7.3.dist-info/WHEEL
simuhw-0.7.3.dist-info/top_level.txt
simuhw-0.7.3.dist-info/RECORD
