Metadata-Version: 2.4
Name: simuhw
Version: 0.7.3
Summary: A behavioral hardware simulator
Home-page: https://github.com/arithy/simuhw
Author: Arihiro Yoshida
Author-email: software@arithy.org
License: MIT License
Requires-Python: <4,>=3.11
License-File: LICENSE
Provides-Extra: dev
Requires-Dist: softfloatpy; extra == "dev"
Requires-Dist: pytest; extra == "dev"
Requires-Dist: mypy; extra == "dev"
Requires-Dist: flake8; extra == "dev"
Provides-Extra: doc
Requires-Dist: softfloatpy; extra == "doc"
Requires-Dist: sphinx; extra == "doc"
Requires-Dist: sphinx-rtd-theme; extra == "doc"
Requires-Dist: myst-parser; extra == "doc"
Dynamic: license-file
